elm/__init__.py
elm/__main__.py
elm/__version__.py
elm/elm.py
elm/elm.yaml
elm/interpreter.py
elm/obd_message.py
elm/plugins/task_ecu_11F1.py
elm/plugins/task_erase_mem_result.py
elm/plugins/task_erase_memory.py
elm/plugins/task_hardware_reset.py
elm/plugins/task_mt05_read_mem_addr.py
elm/plugins/task_mt05_start_routine.py
elm/plugins/task_mt05_stop_routine.py
elm/plugins/task_mt05_write_mem_addr.py
elm/plugins/task_request_seed.py
obd_dictionary/__init__.py
obd_dictionary/__main__.py
ELM327_emulator-3.0.3.dist-info/LICENSE
ELM327_emulator-3.0.3.dist-info/METADATA
ELM327_emulator-3.0.3.dist-info/WHEEL
ELM327_emulator-3.0.3.dist-info/entry_points.txt
ELM327_emulator-3.0.3.dist-info/top_level.txt
ELM327_emulator-3.0.3.dist-info/RECORD
