Metadata-Version: 2.1
Name: ELM327-emulator
Version: 3.0.3
Summary: ELM327 Emulator for testing software interfacing OBDII via ELM327 adapter
Home-page: https://github.com/Ircama/ELM327-emulator
Author: Ircama
License: CC-BY-NC-SA-4.0
Keywords: elm327 emulator obdii obd2 torque simulation simulator can-bus automotive
Classifier: Operating System :: POSIX :: Linux
Classifier: Operating System :: MacOS :: MacOS X
Classifier: Operating System :: POSIX
Classifier: Operating System :: POSIX :: BSD
Classifier: Operating System :: Microsoft :: Windows
Classifier: License :: Other/Proprietary License
Classifier: Topic :: Communications
Classifier: Topic :: Software Development :: Libraries :: Python Modules
Classifier: Programming Language :: Python :: 3 :: Only
Classifier: Development Status :: 5 - Production/Stable
Classifier: Intended Audience :: Manufacturing
Classifier: Intended Audience :: Telecommunications Industry
Classifier: Topic :: System :: Emulators
Classifier: Intended Audience :: Developers
Requires-Python: >3.5
License-File: LICENSE
Requires-Dist: python-daemon
Requires-Dist: pyyaml
Requires-Dist: obd
Requires-Dist: pyreadline3; platform_system == "Windows"
